djangocms_blog_highlight_posts/__init__.py
djangocms_blog_highlight_posts/admin.py
djangocms_blog_highlight_posts/apps.py
djangocms_blog_highlight_posts/locale/en/LC_MESSAGES/django.mo
djangocms_blog_highlight_posts/locale/en/LC_MESSAGES/django.po
djangocms_blog_highlight_posts/locale/fr/LC_MESSAGES/django.mo
djangocms_blog_highlight_posts/locale/fr/LC_MESSAGES/django.po
djangocms_blog_highlight_posts/migrations/0001_initial.py
djangocms_blog_highlight_posts/migrations/__init__.py
djangocms_blog_highlight_posts/models.py
djangocms_blog_highlight_posts/urls.py
djangocms_blog_highlight_posts/views.py
djangocms_blog_highlight_posts-0.0.3.dist-info/LICENSE
djangocms_blog_highlight_posts-0.0.3.dist-info/WHEEL
djangocms_blog_highlight_posts-0.0.3.dist-info/METADATA
djangocms_blog_highlight_posts-0.0.3.dist-info/RECORD
